benlink/__init__.py
benlink/audio.py
benlink/command.py
benlink/controller.py
benlink/link.py
benlink/examples/audiomonitor.py
benlink/examples/audiotransmit.py
benlink/protocol/__init__.py
benlink/protocol/audio.py
benlink/protocol/command/__init__.py
benlink/protocol/command/bitfield.py
benlink/protocol/command/bss_settings.py
benlink/protocol/command/common.py
benlink/protocol/command/dev_info.py
benlink/protocol/command/dev_state_var.py
benlink/protocol/command/gaia_frame.py
benlink/protocol/command/ht_send_data.py
benlink/protocol/command/message.py
benlink/protocol/command/notification.py
benlink/protocol/command/pf.py
benlink/protocol/command/phone_status.py
benlink/protocol/command/power_status.py
benlink/protocol/command/rf_ch.py
benlink/protocol/command/settings.py
benlink/protocol/command/status.py
benlink-0.1.0.dist-info/LICENSE
benlink-0.1.0.dist-info/METADATA
benlink-0.1.0.dist-info/WHEEL
benlink-0.1.0.dist-info/top_level.txt
benlink-0.1.0.dist-info/RECORD
