Metadata-Version: 2.2
Name: benlink
Version: 0.1.0
Summary: A library for Bluetooth communication with Benshi radios like the Vero VR-N76, RadioOddity GA5WB, and BTech UV-Pro.
Author-email: Kyle Husmann <benlink@kylehusmann.com>
License: Apache-2.0
Project-URL: Homepage, https://github.com/khusmann/benlink
Project-URL: Bug Tracker, https://github.com/khusmann/benlink/issues
Classifier: Programming Language :: Python :: 3
Classifier: License :: OSI Approved :: Apache Software License
Classifier: Operating System :: OS Independent
Classifier: Intended Audience :: Developers
Classifier: Topic :: Software Development :: Libraries
Classifier: Topic :: System :: Hardware
Classifier: Topic :: Communications
Requires-Python: >=3.10
License-File: LICENSE
Requires-Dist: typing_extensions>=4.1.0
Requires-Dist: bleak>=0.22.0
Requires-Dist: pydantic>=2.6.0
